MANIFEST.in
Makefile
README.md
requirements.txt
setup.py
pyeqs/__init__.py
pyeqs/bool.py
pyeqs/filter.py
pyeqs/query_builder.py
pyeqs/queryset.py
pyeqs.egg-info/PKG-INFO
pyeqs.egg-info/SOURCES.txt
pyeqs.egg-info/dependency_links.txt
pyeqs.egg-info/requires.txt
pyeqs.egg-info/top_level.txt
pyeqs/dsl/__init__.py
pyeqs/dsl/aggregations.py
pyeqs/dsl/exists.py
pyeqs/dsl/geo.py
pyeqs/dsl/match_all.py
pyeqs/dsl/missing.py
pyeqs/dsl/query_string.py
pyeqs/dsl/range.py
pyeqs/dsl/script_score.py
pyeqs/dsl/sort.py
pyeqs/dsl/term.py
pyeqs/dsl/terms.py
pyeqs/dsl/type.py