Metadata-Version: 1.1
Name: pyeqs
Version: 0.12.0
Summary: Django Querysets-esque implementation for Elasticsearch
Home-page: https://github.com/yipit/pyeqs
Author: Andrew Gross
Author-email: andrew.w.gross@gmail.com
License: MIT
Platform: UNKNOWN
Classifier: Development Status :: 3 - Alpha
Classifier: Intended Audience :: Developers
Classifier: License :: OSI Approved :: MIT
Classifier: Natural Language :: English
Classifier: Operating System :: Microsoft
Classifier: Operating System :: POSIX
Classifier: Programming Language :: Python
Classifier: Programming Language :: Python :: 2.6
Classifier: Programming Language :: Python :: 2.7
Classifier: Programming Language :: Python :: 3.3
Classifier: Programming Language :: Python :: 3.4
